{
  "component": "form-field",
  "scope": "form-field",
  "parts": [
    "root",
    "label",
    "control",
    "helper",
    "error",
    "status"
  ],
  "states": [
    "idle",
    "hover",
    "focus",
    "active",
    "disabled",
    "loading",
    "error"
  ],
  "tokens": [
    "chips.comp.form-field.label.color",
    "chips.comp.form-field.control.surface.idle",
    "chips.comp.form-field.control.border.idle",
    "chips.comp.form-field.control.border.error",
    "chips.comp.form-field.helper.color",
    "chips.comp.form-field.error.color",
    "chips.comp.form-field.focus.outline"
  ],
  "iframe": {
    "requiredSandbox": true,
    "lifecycleEvents": [
      "ready",
      "error"
    ]
  }
}
